django_navigation_manager
