Metadata-Version: 1.0
Name: django-navigation-manager
Version: 0.0.10dev
Summary: Django application that helps other applications declare navigation bar items.
Home-page: projects.airtonix.net/project/django-navigation-manager
Author: Zenobius Jiricek
Author-email: airtonix@gmail.com
License: LICENSE.md
Platform: UNKNOWN
